[{"season": "2018-19", "awards": [{"position": "1", "value": 624.5, "perc": 0.25}, {"position": "2", "value": 437.15000000000003, "perc": 0.175}, {"position": "3", "value": 312.25, "perc": 0.125}, {"position": "4", "value": 224.8, "perc": 0.09}, {"position": "5", "value": 158.60000000000002, "perc": 0.0635}, {"position": "6", "value": 112.4, "perc": 0.045}, {"position": "7", "value": 81.2, "perc": 0.0325}, {"position": "8", "value": 59.95, "perc": 0.024}, {"position": "9", "value": 49.95, "perc": 0.02}, {"position": "1c", "value": 199.85000000000002, "perc": 0.08}, {"position": "2c", "value": 87.45, "perc": 0.035}, {"position": "3c", "value": 37.45, "perc": 0.015}, {"position": "4c", "value": 12.5, "perc": 0.005}, {"position": "tot", "value": 74.95, "perc": 0.03}, {"position": "totD", "value": 25, "perc": 0.01}], "fines": []}, {"season": "2019-20", "awards": [{"position": "1", "value": 721.1, "perc": 0.25}, {"position": "2", "value": 504.8, "perc": 0.175}, {"position": "3", "value": 360.55, "perc": 0.125}, {"position": "4", "value": 259.6, "perc": 0.09}, {"position": "5", "value": 183.15, "perc": 0.0635}, {"position": "6", "value": 129.8, "perc": 0.045}, {"position": "7", "value": 93.75, "perc": 0.0325}, {"position": "8", "value": 69.25, "perc": 0.024}, {"position": "9", "value": 57.7, "perc": 0.02}, {"position": "1c", "value": 230.75, "perc": 0.08}, {"position": "2c", "value": 100.95, "perc": 0.035}, {"position": "3c", "value": 43.25, "perc": 0.015}, {"position": "4c", "value": 14.4, "perc": 0.005}, {"position": "tot", "value": 86.55000000000001, "perc": 0.03}, {"position": "totD", "value": 28.85, "perc": 0.01}], "fines": []}, {"season": "2020-21", "awards": [{"position": "1", "value": 866.0500000000001, "perc": 0.25}, {"position": "2", "value": 606.2, "perc": 0.175}, {"position": "3", "value": 433, "perc": 0.125}, {"position": "4", "value": 311.75, "perc": 0.09}, {"position": "5", "value": 219.95000000000002, "perc": 0.0635}, {"position": "6", "value": 155.9, "perc": 0.045}, {"position": "7", "value": 112.60000000000001, "perc": 0.0325}, {"position": "8", "value": 83.15, "perc": 0.024}, {"position": "9", "value": 69.3, "perc": 0.02}, {"position": "1c", "value": 277.15000000000003, "perc": 0.08}, {"position": "2c", "value": 121.25, "perc": 0.035}, {"position": "3c", "value": 51.95, "perc": 0.015}, {"position": "4c", "value": 17.3, "perc": 0.005}, {"position": "tot", "value": 103.9, "perc": 0.03}, {"position": "totD", "value": 34.65, "perc": 0.01}], "fines": [{"aliquot": 0.4, "percLimit": 1.5, "moneyLimit": 360.5}, {"aliquot": 0.6, "percLimit": 1.75, "moneyLimit": 420.6}, {"aliquot": 0.9, "percLimit": 2, "moneyLimit": 480.7}, {"aliquot": 1.3, "percLimit": 2.25, "moneyLimit": 540.8}]}, {"season": "2021-22", "awards": [{"position": "1", "value": 1039.9, "perc": 0.25}, {"position": "2", "value": 736.25, "perc": 0.177}, {"position": "3", "value": 532.45, "perc": 0.128}, {"position": "4", "value": 391, "perc": 0.094}, {"position": "5", "value": 287, "perc": 0.069}, {"position": "6", "value": 212.15, "perc": 0.051}, {"position": "7", "value": 158.05, "perc": 0.038}, {"position": "8", "value": 116.45, "perc": 0.028}, {"position": "9", "value": 83.2, "perc": 0.02}, {"position": "1c", "value": 332.75, "perc": 0.08}, {"position": "2c", "value": 145.6, "perc": 0.035}, {"position": "3c", "value": 62.400000000000006, "perc": 0.015}, {"position": "4c", "value": 20.8, "perc": 0.005}, {"position": "totD", "value": 41.6, "perc": 0.01}], "fines": [{"aliquot": 0.4, "percLimit": 1.5, "moneyLimit": 433}, {"aliquot": 0.6, "percLimit": 1.75, "moneyLimit": 505.2}, {"aliquot": 0.9, "percLimit": 2, "moneyLimit": 577.4}, {"aliquot": 1.3, "percLimit": 2.25, "moneyLimit": 649.5}]}, {"season": "2022-23", "awards": [{"position": "1", "value": 995.7, "perc": 0.26}, {"position": "2", "value": 658.7, "perc": 0.172}, {"position": "3", "value": 440.40000000000003, "perc": 0.115}, {"position": "4", "value": 298.7, "perc": 0.078}, {"position": "5", "value": 206.8, "perc": 0.054}, {"position": "6", "value": 141.70000000000002, "perc": 0.037}, {"position": "7", "value": 95.75, "perc": 0.025}, {"position": "8", "value": 61.25, "perc": 0.016}, {"position": "9", "value": 0, "perc": 0}, {"position": "1c", "value": 528.45, "perc": 0.138}, {"position": "2c", "value": 233.60000000000002, "perc": 0.061}, {"position": "3c", "value": 95.75, "perc": 0.025}, {"position": "4c", "value": 34.45, "perc": 0.009}, {"position": "totD", "value": 38.300000000000004, "perc": 0.01}], "fines": [{"aliquot": 0.35, "percLimit": 1.5, "moneyLimit": 520}, {"aliquot": 0.75, "percLimit": 1.65, "moneyLimit": 571.9}, {"aliquot": 1.2, "percLimit": 1.8, "moneyLimit": 623.9}, {"aliquot": 1.7, "percLimit": 1.95, "moneyLimit": 675.9}]}, {"season": "2023-24", "awards": [{"position": "1", "value": 918.3000000000001, "perc": 0.26}, {"position": "2", "value": 607.5, "perc": 0.172}, {"position": "3", "value": 406.15000000000003, "perc": 0.115}, {"position": "4", "value": 275.5, "perc": 0.078}, {"position": "5", "value": 190.70000000000002, "perc": 0.054}, {"position": "6", "value": 130.70000000000002, "perc": 0.037}, {"position": "7", "value": 88.30000000000001, "perc": 0.025}, {"position": "8", "value": 56.5, "perc": 0.016}, {"position": "9", "value": 0, "perc": 0}, {"position": "1c", "value": 423.85, "perc": 0.12}, {"position": "2c", "value": 187.20000000000002, "perc": 0.053}, {"position": "3c", "value": 77.7, "perc": 0.022}, {"position": "4c", "value": 28.25, "perc": 0.008}, {"position": "1c2", "value": 105.95, "perc": 0.03}, {"position": "totD", "value": 35.300000000000004, "perc": 0.01}], "fines": [{"aliquot": 0.35, "percLimit": 1.45, "moneyLimit": 555.3}, {"aliquot": 0.75, "percLimit": 1.6, "moneyLimit": 612.7}, {"aliquot": 1.2, "percLimit": 1.75, "moneyLimit": 670.2}, {"aliquot": 1.7, "percLimit": 1.9, "moneyLimit": 727.6}]}, {"season": "2024-25", "awards": [{"position": "1", "value": 783.85, "perc": 0.26}, {"position": "2", "value": 518.5500000000001, "perc": 0.172}, {"position": "3", "value": 346.70000000000005, "perc": 0.115}, {"position": "4", "value": 235.15, "perc": 0.078}, {"position": "5", "value": 162.8, "perc": 0.054}, {"position": "6", "value": 111.55000000000001, "perc": 0.037}, {"position": "7", "value": 75.35000000000001, "perc": 0.025}, {"position": "8", "value": 48.25, "perc": 0.016}, {"position": "9", "value": 0, "perc": 0}, {"position": "1c", "value": 232.15, "perc": 0.077}, {"position": "2c", "value": 144.70000000000002, "perc": 0.048}, {"position": "1el", "value": 114.55000000000001, "perc": 0.038}, {"position": "2el", "value": 75.35000000000001, "perc": 0.025}, {"position": "1ci", "value": 90.45, "perc": 0.03}, {"position": "2ci", "value": 45.2, "perc": 0.015}], "fines": [{"aliquot": 0.35, "percLimit": 1.45, "moneyLimit": 512.13}, {"aliquot": 0.75, "percLimit": 1.6, "moneyLimit": 565.11}, {"aliquot": 1.2, "percLimit": 1.75, "moneyLimit": 618.09}, {"aliquot": 1.7, "percLimit": 1.9, "moneyLimit": 671.07}]}, {"season": "2025-26", "awards": [{"position": "1", "value": 246.45000000000002, "perc": 0.274}, {"position": "2", "value": 162.8, "perc": 0.181}, {"position": "3", "value": 109.75, "perc": 0.122}, {"position": "4", "value": 74.65, "perc": 0.083}, {"position": "5", "value": 51.25, "perc": 0.057}, {"position": "6", "value": 35.1, "perc": 0.039}, {"position": "7", "value": 23.400000000000002, "perc": 0.026}, {"position": "8", "value": 15.3, "perc": 0.017}, {"position": "9", "value": 0, "perc": 0}, {"position": "1c", "value": 92.65, "perc": 0.103}, {"position": "2c", "value": 41.35, "perc": 0.046}, {"position": "1el", "value": 17.1, "perc": 0.019}, {"position": "2el", "value": 6.300000000000001, "perc": 0.007}, {"position": "1ci", "value": 23.400000000000002, "perc": 0.026}, {"position": "2ci", "value": null, "perc": null}], "fines": [{"aliquot": 0.35, "percLimit": 1.45, "moneyLimit": 512.13}, {"aliquot": 0.75, "percLimit": 1.6, "moneyLimit": 565.11}, {"aliquot": 1.2, "percLimit": 1.75, "moneyLimit": 618.09}, {"aliquot": 1.7, "percLimit": 1.9, "moneyLimit": 671.07}]}]